tabeval/__init__.py
tabeval/logger.py
tabeval/version.py
tabeval/benchmark/__init__.py
tabeval/benchmark/utils.py
tabeval/metrics/__init__.py
tabeval/metrics/_utils.py
tabeval/metrics/eval.py
tabeval/metrics/eval_density.py
tabeval/metrics/eval_privacy.py
tabeval/metrics/eval_statistical.py
tabeval/metrics/eval_structure.py
tabeval/metrics/plots.py
tabeval/metrics/scores.py
tabeval/metrics/core/__init__.py
tabeval/metrics/core/metric.py
tabeval/metrics/representations/OneClass.py
tabeval/metrics/representations/__init__.py
tabeval/metrics/representations/networks.py
tabeval/plugins/__init__.py
tabeval/plugins/core/__init__.py
tabeval/plugins/core/constraints.py
tabeval/plugins/core/dataloader.py
tabeval/plugins/core/dataset.py
tabeval/plugins/core/distribution.py
tabeval/plugins/core/plugin.py
tabeval/plugins/core/schema.py
tabeval/plugins/core/serializable.py
tabeval/plugins/core/models/RGCNConv.py
tabeval/plugins/core/models/__init__.py
tabeval/plugins/core/models/aim.py
tabeval/plugins/core/models/bnaf.py
tabeval/plugins/core/models/convnet.py
tabeval/plugins/core/models/factory.py
tabeval/plugins/core/models/feature_encoder.py
tabeval/plugins/core/models/flows.py
tabeval/plugins/core/models/functions.py
tabeval/plugins/core/models/gan.py
tabeval/plugins/core/models/goggle.py
tabeval/plugins/core/models/image_gan.py
tabeval/plugins/core/models/layers.py
tabeval/plugins/core/models/mlp.py
tabeval/plugins/core/models/tabnet.py
tabeval/plugins/core/models/tabular_aim.py
tabeval/plugins/core/models/tabular_arf.py
tabeval/plugins/core/models/tabular_encoder.py
tabeval/plugins/core/models/tabular_flows.py
tabeval/plugins/core/models/tabular_gan.py
tabeval/plugins/core/models/tabular_goggle.py
tabeval/plugins/core/models/tabular_great.py
tabeval/plugins/core/models/tabular_scm.py
tabeval/plugins/core/models/tabular_vae.py
tabeval/plugins/core/models/transformer.py
tabeval/plugins/core/models/ts_gan.py
tabeval/plugins/core/models/ts_model.py
tabeval-2025.8.10.dist-info/METADATA
tabeval-2025.8.10.dist-info/WHEEL
tabeval-2025.8.10.dist-info/licenses/LICENSE
tabeval-2025.8.10.dist-info/RECORD
