Metadata-Version: 2.4
Name: tabeval
Version: 2025.8.10
Summary: A comprehensive Python framework for evaluating synthetic tabular data generation methods
Author-email: Xiangjian Jiang <silencejiang12138@gmail.com>
License:                                  Apache License
License-File: LICENSE
Keywords: data generation,evaluation framework,synthetic data,tabular data
Classifier: License :: OSI Approved :: Apache Software License
Classifier: Programming Language :: Python :: 3
Classifier: Programming Language :: Python :: 3.10
Requires-Python: >=3.10
Requires-Dist: arfpy
Requires-Dist: be-great
Requires-Dist: build
Requires-Dist: cloudpickle
Requires-Dist: decaf-synthetic-data
Requires-Dist: fflows
Requires-Dist: flake8
Requires-Dist: geomloss
Requires-Dist: hatchling
Requires-Dist: importlib-metadata
Requires-Dist: ipykernel
Requires-Dist: lifelines
Requires-Dist: loguru
Requires-Dist: monai
Requires-Dist: myst-parser
Requires-Dist: networkx
Requires-Dist: nflows
Requires-Dist: numpy
Requires-Dist: opacus
Requires-Dist: optuna
Requires-Dist: pandas
Requires-Dist: pgmpy
Requires-Dist: pycox
Requires-Dist: pydantic
Requires-Dist: pykeops
Requires-Dist: pylint
Requires-Dist: pytest
Requires-Dist: redis
Requires-Dist: scikit-learn
Requires-Dist: scipy
Requires-Dist: setuptools==75.1.0
Requires-Dist: shap
Requires-Dist: sphinx
Requires-Dist: sphinx-book-theme
Requires-Dist: sphinx-rtd-theme
Requires-Dist: tabpfn
Requires-Dist: tenacity
Requires-Dist: torch
Requires-Dist: tqdm
Requires-Dist: tsai
Requires-Dist: xgboost
Requires-Dist: xgbse
Provides-Extra: all
Requires-Dist: dgl; extra == 'all'
Requires-Dist: torch-geometric; extra == 'all'
Requires-Dist: torch-scatter; extra == 'all'
Requires-Dist: torch-sparse; extra == 'all'
